apollo/UI.py
apollo/__init__.py
apollo/analysis.py
apollo/config.py
apollo/crater_predictor.py
apollo/data_processor.py
apollo/download_models.py
ApolloCraterDetectionTool-1.0.dist-info/AUTHORS.txt
ApolloCraterDetectionTool-1.0.dist-info/LICENSE.txt
ApolloCraterDetectionTool-1.0.dist-info/METADATA
ApolloCraterDetectionTool-1.0.dist-info/WHEEL
ApolloCraterDetectionTool-1.0.dist-info/top_level.txt
ApolloCraterDetectionTool-1.0.dist-info/RECORD
