Metadata-Version: 2.1
Name: ApolloCraterDetectionTool
Version: 1.0
Summary: Detection Tool
Home-page: https://github.com/ese-msc-2022/
Author: ADS project Team Nene
License-File: LICENSE.txt
License-File: AUTHORS.txt
